trapcards/__init__.py
trapcards/justdetective.py
trapcards/justmathgenius.py
trapcards-0.0.3.dist-info/METADATA
trapcards-0.0.3.dist-info/RECORD
trapcards-0.0.3.dist-info/WHEEL
trapcards-0.0.3.dist-info/top_level.txt
