Metadata-Version: 2.1
Name: trapcards
Version: 0.0.3
Summary: A collections of mathmatic dev kits that the author designed for daily coding.
Home-page: https://github.com/pypa/sampleproject
Author: Rabbinhat
Author-email: zhengyangma9517@gmail.com
License: UNKNOWN
Platform: UNKNOWN
Classifier: Programming Language :: Python :: 3
Classifier: License :: OSI Approved :: MIT License
Classifier: Operating System :: OS Independent
